pptoml/__about__.py
pptoml/__init__.py
pptoml/__main__.py
pptoml/cli.py
pptoml/enums.py
pptoml/fetch.py
pptoml/generate.py
pptoml/inout.py
pptoml/mod.py
pptoml/validate.py
pptoml-0.3.0.dist-info/METADATA
pptoml-0.3.0.dist-info/WHEEL
pptoml-0.3.0.dist-info/entry_points.txt
pptoml-0.3.0.dist-info/licenses/LICENSE-APACHE
pptoml-0.3.0.dist-info/licenses/LICENSE-MIT
pptoml-0.3.0.dist-info/RECORD
