Metadata-Version: 2.1
Name: pptoml
Version: 0.3.0
Summary: Library and CLI tool for parsing, validating, modifying, and updating `pyproject.toml` files. 
Project-URL: Documentation, https://github.com/patrickarmengol/pptoml#readme
Project-URL: Issues, https://github.com/patrickarmengol/pptoml/issues
Project-URL: Source, https://github.com/patrickarmengol/pptoml
Author-email: Patrick Armengol <patrickarmengol@protonmail.com>
License-File: LICENSE-APACHE
License-File: LICENSE-MIT
Classifier: Development Status :: 4 - Beta
Classifier: Programming Language :: Python
Classifier: Programming Language :: Python :: 3.7
Classifier: Programming Language :: Python :: 3.8
Classifier: Programming Language :: Python :: 3.9
Classifier: Programming Language :: Python :: 3.10
Classifier: Programming Language :: Python :: 3.11
Classifier: Programming Language :: Python :: Implementation :: CPython
Classifier: Programming Language :: Python :: Implementation :: PyPy
Requires-Python: >=3.7
Requires-Dist: questionary
Requires-Dist: tomli
Requires-Dist: typer[all]
Requires-Dist: validate-pyproject[all]
